htpwd
