Metadata-Version: 1.1
Name: htpwd
Version: 0.1.1
Summary: A web Interface for users change their own passwords on a
Home-page: https://github.com/gcavalcante8808/htpwd
Author: Gabriel Abdalla Cavalcante
Author-email: gabriel.cavalcante88@gmail.com
License: License :: OSI Approved :: Apache Software License
Platform: UNKNOWN
Classifier: Development Status :: 5 - Production/Stable
Classifier: Environment :: Web Environment
Classifier: Framework :: Flask
Classifier: Intended Audience :: Information Technology
Classifier: Intended Audience :: System Administrators
Classifier: Intended Audience :: End Users/Desktop
Classifier: License :: OSI Approved :: Apache Software License
Classifier: Programming Language :: Python
Classifier: Programming Language :: Python :: 3
Classifier: Programming Language :: Python :: 2
